tpedit/gui.py
tpedit/main.py
tpedit/tpedit_mockup.py
tpedit/__init__.py
tpedit/tests/test_temp.py
tpedit/tests/__init__.py
TPEdit-0.1.0.dist-info/DESCRIPTION.rst
TPEdit-0.1.0.dist-info/METADATA
TPEdit-0.1.0.dist-info/metadata.json
TPEdit-0.1.0.dist-info/RECORD
TPEdit-0.1.0.dist-info/top_level.txt
TPEdit-0.1.0.dist-info/WHEEL
