Metadata-Version: 2.0
Name: TPEdit
Version: 0.1.0
Summary: A Test Program editor and diff tool for Focused Test
